{"info/num_env_steps_sampled": 6640800, "info/num_env_steps_trained": 6640800, "info/num_agent_steps_sampled": 54367200, "info/num_agent_steps_trained": 54367200, "stats/episode_reward_max": -774876.9880115588, "stats/episode_reward_min": -2721519.193160672, "stats/episode_reward_mean": -1895977.3492688334, "stats/episode_len_mean": 11999.0, "stats/episodes_this_iter": 5, "stats/num_faulty_episodes": 0, "stats/num_healthy_workers": 5, "stats/num_in_flight_async_reqs": 0, "stats/num_remote_worker_restarts": 0, "stats/num_agent_steps_sampled": 54367200, "stats/num_agent_steps_trained": 54367200, "stats/num_env_steps_sampled": 6640800, "stats/num_env_steps_trained": 6640800, "stats/num_env_steps_sampled_this_iter": 4000, "stats/num_env_steps_trained_this_iter": 4000, "stats/timesteps_total": 6640800, "stats/num_steps_trained_this_iter": 4000, "stats/agent_timesteps_total": 54367200, "stats/done": false, "stats/episodes_total": 150, "stats/training_iteration": 450, "stats/trial_id": "default", "stats/experiment_id": "19a91755d4ba4d10b6f24a949dfa23aa", "stats/date": "2023-04-25_10-01-23", "stats/timestamp": 1682431283, "stats/time_this_iter_s": 63.20956254005432, "stats/time_total_s": 28057.073651075363, "stats/pid": 689579, "stats/hostname": "christine-HP-Spectre-x360-Convertible-13-ap0xxx", "stats/node_ip": "10.9.2.94", "stats/time_since_restore": 28057.073651075363, "stats/timesteps_since_restore": 0, "stats/iterations_since_restore": 450, "stats/warmup_time": 12.087690114974976, "learner_agent_B/allreduce_latency": 0.0, "learner_agent_B/grad_gnorm": 97.49141780734062, "learner_agent_B/cur_kl_coeff": 3.3154899349305746, "learner_agent_B/cur_lr": 5.0000000000000016e-05, "learner_agent_B/total_loss": 7.845392294228077, "learner_agent_B/policy_loss": -0.037428848494649475, "learner_agent_B/vf_loss": 7.821063187221686, "learner_agent_B/vf_explained_var": -3.903551648060481e-05, "learner_agent_B/kl": 0.018627108834154103, "learner_agent_B/entropy": 6.0847096736232436, "learner_agent_B/entropy_coeff": 0.0, "learner_agent_E/allreduce_latency": 0.0, "learner_agent_E/grad_gnorm": 11.593659744163354, "learner_agent_E/cur_kl_coeff": 1.175253521334412, "learner_agent_E/cur_lr": 5.0000000000000016e-05, "learner_agent_E/total_loss": 9.568148868282636, "learner_agent_E/policy_loss": -0.0749149112899128, "learner_agent_E/vf_loss": 9.624772630135219, "learner_agent_E/vf_explained_var": 0.0003123046830296516, "learner_agent_E/kl": 0.015563540544827389, "learner_agent_E/entropy": 4.653756615022818, "learner_agent_E/entropy_coeff": 0.0, "learner_agent_A/allreduce_latency": 0.0, "learner_agent_A/grad_gnorm": 11.641062756379446, "learner_agent_A/cur_kl_coeff": 2.0698440441206576, "learner_agent_A/cur_lr": 5.0000000000000016e-05, "learner_agent_A/total_loss": 9.601811195413271, "learner_agent_A/policy_loss": -0.03507497710864603, "learner_agent_A/vf_loss": 9.623992994427681, "learner_agent_A/vf_explained_var": 0.0004323553293943405, "learner_agent_A/kl": 0.006229039639890621, "learner_agent_A/entropy": 18.03588104645411, "learner_agent_A/entropy_coeff": 0.0, "learner_agent_H/allreduce_latency": 0.0, "learner_agent_H/grad_gnorm": 112.36308299501736, "learner_agent_H/cur_kl_coeff": 1.3584834803183494, "learner_agent_H/cur_lr": 5.0000000000000016e-05, "learner_agent_H/total_loss": 6.458203059434891, "learner_agent_H/policy_loss": -0.02669539956744605, "learner_agent_H/vf_loss": 6.467667308449745, "learner_agent_H/vf_explained_var": -0.007686768844723702, "learner_agent_H/kl": 0.012684100961400147, "learner_agent_H/entropy": 22.347328707575798, "learner_agent_H/entropy_coeff": 0.0, "learner_agent_D/allreduce_latency": 0.0, "learner_agent_D/grad_gnorm": 6.636341808736324, "learner_agent_D/cur_kl_coeff": 2.010298190003632, "learner_agent_D/cur_lr": 5.0000000000000016e-05, "learner_agent_D/total_loss": 8.036976603170237, "learner_agent_D/policy_loss": -0.04275326068454888, "learner_agent_D/vf_loss": 8.067085578044255, "learner_agent_D/vf_explained_var": -0.0012242979059616725, "learner_agent_D/kl": 0.006289742278886858, "learner_agent_D/entropy": 3.261213009804487, "learner_agent_D/entropy_coeff": 0.0, "learner_agent_G/allreduce_latency": 0.0, "learner_agent_G/grad_gnorm": 67.66748207161824, "learner_agent_G/cur_kl_coeff": 2.981078868500731, "learner_agent_G/cur_lr": 5.0000000000000016e-05, "learner_agent_G/total_loss": 9.19088281840086, "learner_agent_G/policy_loss": 0.014390350755032462, "learner_agent_G/vf_loss": 8.898142184813818, "learner_agent_G/vf_explained_var": 0.0003969678655266762, "learner_agent_G/kl": 0.09337233167746793, "learner_agent_G/entropy": 14.135203305880228, "learner_agent_G/entropy_coeff": 0.0, "_timestamp": 1682431283.982169, "_runtime": 28099.129473924637, "_step": 449}